Metadata-Version: 1.1
Name: Telegrambotmaker
Version: 0.0.1
Summary: Telegram API
Home-page: UNKNOWN
Author: UNKNOWN
Author-email: UNKNOWN
License: UNKNOWN
Platform: UNKNOWN
Requires: requests
